strings/routes.py
strings/sql_query.py
todolistmodule/__init__.py
todolistmodule/todolistdao.py
todolistwebapi/__init__.py
todolistwebapi/todolistwebapi.py
todolistmodule-0.0.11.dist-info/METADATA
todolistmodule-0.0.11.dist-info/WHEEL
todolistmodule-0.0.11.dist-info/top_level.txt
todolistmodule-0.0.11.dist-info/RECORD
