Metadata-Version: 2.1
Name: todolistmodule
Version: 0.0.11
Summary: To Do List Module - Task Management - Package
Author-email: diego vasque maldonado <diegoomal13@gmail.com>
Project-URL: Homepage, https://github.com/Diegoomal/devops_trab_final
Project-URL: Bug Tracker, https://github.com/Diegoomal/devops_trab_final/issues
Requires-Python: >=3.9
